zsxq_mcp/__init__.py
zsxq_mcp/__main__.py
zsxq_mcp/client.py
zsxq_mcp/config.py
zsxq_mcp/server.py
zsxq_mcp-0.2.4.dist-info/METADATA
zsxq_mcp-0.2.4.dist-info/WHEEL
zsxq_mcp-0.2.4.dist-info/entry_points.txt
zsxq_mcp-0.2.4.dist-info/RECORD
