Metadata-Version: 2.4
Name: zsxq-mcp
Version: 0.2.4
Summary: MCP server for publishing content to Zhishixingqiu (知识星球)
Requires-Python: >=3.10
Requires-Dist: fastmcp>=0.2.0
Requires-Dist: httpx>=0.27.0
Requires-Dist: python-dotenv>=1.0.0
Provides-Extra: dev
Requires-Dist: pytest-asyncio>=0.23.0; extra == 'dev'
Requires-Dist: pytest>=8.0.0; extra == 'dev'
